scavenger/__init__.py
scavenger/agent.py
scavenger/config.py
scavenger/internal/__init__.py
scavenger/internal/banner.py
scavenger/internal/client.py
scavenger/internal/constant.py
scavenger/internal/invocation_registry.py
scavenger/internal/model.py
scavenger/internal/patch.py
scavenger/internal/scan.py
scavenger/internal/scheduler.py
scavenger/internal/util.py
scavenger/model/CodeBasePublication_pb2.py
scavenger/model/CodeBasePublication_pb2.pyi
scavenger/model/CodeBasePublication_pb2_grpc.py
scavenger/model/CommonPublicationData_pb2.py
scavenger/model/CommonPublicationData_pb2.pyi
scavenger/model/CommonPublicationData_pb2_grpc.py
scavenger/model/GetConfig_pb2.py
scavenger/model/GetConfig_pb2.pyi
scavenger/model/GetConfig_pb2_grpc.py
scavenger/model/GrpcAgentService_pb2.py
scavenger/model/GrpcAgentService_pb2.pyi
scavenger/model/GrpcAgentService_pb2_grpc.py
scavenger/model/InitConfig_pb2.py
scavenger/model/InitConfig_pb2.pyi
scavenger/model/InitConfig_pb2_grpc.py
scavenger/model/InvocationDataPublication_pb2.py
scavenger/model/InvocationDataPublication_pb2.pyi
scavenger/model/InvocationDataPublication_pb2_grpc.py
scavenger/model/__init__.py
scavenger_agent_python-0.1.2.dist-info/LICENSE
scavenger_agent_python-0.1.2.dist-info/WHEEL
scavenger_agent_python-0.1.2.dist-info/METADATA
scavenger_agent_python-0.1.2.dist-info/RECORD
