Metadata-Version: 2.1
Name: scavenger-agent-python
Version: 0.1.2
Summary: 
Author: dbgsprw
Author-email: dbgsprw@gmail.com
Requires-Python: >=3.7,<4.0
Classifier: Programming Language :: Python :: 3
Classifier: Programming Language :: Python :: 3.7
Classifier: Programming Language :: Python :: 3.8
Classifier: Programming Language :: Python :: 3.9
Classifier: Programming Language :: Python :: 3.10
Classifier: Programming Language :: Python :: 3.11
Requires-Dist: apscheduler (>=3.10.0,<4.0.0)
Requires-Dist: dataclass-builder (>=1.2.0,<2.0.0)
Requires-Dist: grpcio (>=1.51.1,<2.0.0)
Requires-Dist: path (>=16.6.0,<17.0.0)
Requires-Dist: protobuf (>=4.21.12,<5.0.0)
Requires-Dist: requests (>=2.28.2,<3.0.0)
